<?xml version="1.0" encoding="UTF-8"?>
<!DOCTYPE suite SYSTEM "https://testng.org/testng-1.0.dtd">
<suite parallel="tests" name="Suite">
		<groups>
			<run>
				<include name="Purchase"></include>
			</run>
		</groups>
	<test parallel="false" thread-count="5" name="Submit order test">
		<classes>
			<class name="framedesign.tests.submitOrderTest" />
		</classes>
	</test>
	<test thread-count="5" name="Login error validation test">
		<classes>
			<class name="framedesign.tests.LoginErrorValidationTest" />
		</classes>
	</test>
</suite> <!--
Suite -->
